<?xml version="1.0" encoding="utf-8" ?>
<dwsync>
<file name="01 Ch25Foner.ppsx" server="ftp.bizland.com" local="128538684540000000" remote="131345004600000000" Dst="2" />
<file name="01unit 1 51-100 revix brit.pdf" server="ftp.bizland.com" local="128535160880000000" remote="131345004600000000" Dst="2" />
<file name="02 CAS_CH29.ppsx" server="ftp.bizland.com" local="128538686160000000" remote="131345004600000000" Dst="2" />
<file name="02 Ch21Foner.ppsx" server="ftp.bizland.com" local="128538676140000000" remote="131345005200000000" Dst="2" />
<file name="02CAS_CH24.ppsx" server="ftp.bizland.com" local="128538671420000000" remote="131345005200000000" Dst="2" />
<file name="02UNIT 1 150-204 mike.pdf" server="ftp.bizland.com" local="128535161400000000" remote="131345005200000000" Dst="2" />
<file name="03 CAS_CH28.ppsx" server="ftp.bizland.com" local="128538681120000000" remote="131345005200000000" Dst="2" />
<file name="03Ch19Foner.ppt" server="ftp.bizland.com" local="128538672840000000" remote="131345005200000000" Dst="2" />
<file name="03UNIT 1150-204 matt.pdf" server="ftp.bizland.com" local="128535162040000000" remote="131345005200000000" Dst="2" />
<file name="04unit2 1-50Jason Patt.pdf" server="ftp.bizland.com" local="128535162400000000" remote="131345005200000000" Dst="2" />
<file name="05unit2 43-92 alisa.pdf" server="ftp.bizland.com" local="128535164360000000" remote="131345005200000000" Dst="2" />
<file name="07Unit 3 vocab 26 -41 and unit 4 1-25james.pdf" server="ftp.bizland.com" local="128535162860000000" remote="131345005200000000" Dst="2" />
<file name="08Unit 4 Vocab 76-90 mattg.pdf" server="ftp.bizland.com" local="128535163940000000" remote="131345005200000000" Dst="2" />
<file name="09unit5 76-125Julia Starkov.pdf" server="ftp.bizland.com" local="128535164100000000" remote="131345005200000000" Dst="2" />
<file name="12unit 5 1825-50 Christina76-125.pdf" server="ftp.bizland.com" local="128535164560000000" remote="131345005200000000" Dst="2" />
<file name="13unit 5 126-174Megan Wolf.pdf" server="ftp.bizland.com" local="128535164920000000" remote="131345005200000000" Dst="2" />
<file name="1451 - 1620.ppsx" server="ftp.bizland.com" local="128529299120000000" remote="131345005200000000" Dst="2" />
<file name="14Unit 5 and Unit 6 Vocabulary176-182 and 1-40 ashlee.pdf" server="ftp.bizland.com" local="129388780260000000" remote="131345005200000000" Dst="2" />
<file name="15Unit 6 Vocab41-90 jessica.pdf" server="ftp.bizland.com" local="128535167560000000" remote="131345005200000000" Dst="2" />
<file name="16Unit 7 Words 90-140 brit.pdf" server="ftp.bizland.com" local="128535167760000000" remote="131345005200000000" Dst="2" />
<file name="1766-1818.ppsx" server="ftp.bizland.com" local="128529299520000000" remote="131345005200000000" Dst="2" />
<file name="1819-1837.ppsx" server="ftp.bizland.com" local="128529299820000000" remote="131345005200000000" Dst="2" />
<file name="1873 - 1933.ppsx" server="ftp.bizland.com" local="128529301220000000" remote="131345005200000000" Dst="2" />
<file name="1890-1945.ppsx" server="ftp.bizland.com" local="128529300200000000" remote="131345005800000000" Dst="2" />
<file name="1914-1993.ppsx" server="ftp.bizland.com" local="128529299980000000" remote="131345005800000000" Dst="2" />
<file name="1919-1929.ppsx" server="ftp.bizland.com" local="128529300940000000" remote="131345005800000000" Dst="2" />
<file name="1ST IN CLASS ESSAY.pdf" server="ftp.bizland.com" local="128529289780000000" remote="131345005800000000" Dst="2" />
<file name="2-outline.ppsx" server="ftp.bizland.com" local="128535180200000000" remote="131345005800000000" Dst="2" />
<file name="2nd nine weeks 1st essay 0708.pdf" server="ftp.bizland.com" local="128529289240000000" remote="131345005800000000" Dst="2" />
<file name="3 - outline.ppsx" server="ftp.bizland.com" local="128535180780000000" remote="131345005800000000" Dst="2" />
<file name="3rd In Class Essay-1.pdf" server="ftp.bizland.com" local="128529290080000000" remote="131345005800000000" Dst="2" />
<file name="4-outline.ppsx" server="ftp.bizland.com" local="128535182140000000" remote="131345005800000000" Dst="2" />
<file name="4th in class essay for 07-08-1.pdf" server="ftp.bizland.com" local="128529290520000000" remote="131345005800000000" Dst="2" />
<file name="4th In class Essay-1.pdf" server="ftp.bizland.com" local="128529290660000000" remote="131345005800000000" Dst="2" />
<file name="5-outline.ppsx" server="ftp.bizland.com" local="128535183700000000" remote="131345005800000000" Dst="2" />
<file name="AP American History2nd inclassessays.pdf" server="ftp.bizland.com" local="128529289940000000" remote="131345006400000000" Dst="2" />
<file name="Ap_American_History_Jeopardy_Challenge 2.ppt" server="ftp.bizland.com" local="128538688320000000" remote="131345006400000000" Dst="2" />
<file name="Ap_American_History_Jeopardy_Challenge 2.pptx" server="ftp.bizland.com" local="128538688140000000" remote="131345006400000000" Dst="2" />
<file name="BILL GATES.pdf" server="ftp.bizland.com" local="128529286860000000" remote="131345007000000000" Dst="2" />
<file name="CAS_CH05.ppsx" server="ftp.bizland.com" local="128529297040000000" remote="131345008800000000" Dst="2" />
<file name="Ch02Foner.ppsx" server="ftp.bizland.com" local="128529297520000000" remote="131345008800000000" Dst="2" />
<file name="Ch03Foner.ppsx" server="ftp.bizland.com" local="128529297900000000" remote="131345008800000000" Dst="2" />
<file name="Ch04Foner.ppsx" server="ftp.bizland.com" local="128529298380000000" remote="131345009400000000" Dst="2" />
<file name="DBQ Essay.pdf" server="ftp.bizland.com" local="128529291440000000" remote="131345009400000000" Dst="2" />
<file name="James A.pdf" server="ftp.bizland.com" local="128535171720000000" remote="131345010000000000" Dst="2" />
<file name="power point review.ppsx" server="ftp.bizland.com" local="128529296420000000" remote="131345010600000000" Dst="2" />
<file name="PRESIDENTS.pdf" server="ftp.bizland.com" local="128535171860000000" remote="131345010600000000" Dst="2" />
<file name="Sean McDanielessay.pdf" server="ftp.bizland.com" local="128529292060000000" remote="131345010600000000" Dst="2" />
<file name="Tanya Littlefieldessay.pdf" server="ftp.bizland.com" local="128529291940000000" remote="131345012400000000" Dst="2" />
<file name="the 1960's.ppsx" server="ftp.bizland.com" local="128529302840000000" remote="131345012400000000" Dst="2" />
<file name="unit 10 voc ap 51-151 hist.pdf" server="ftp.bizland.com" local="128535168360000000" remote="131345012400000000" Dst="2" />
<file name="LaurenHarperTravelingSoldier.wmv" server="ftp.bizland.com" local="128548335240000000" remote="131345010600000000" Dst="2" />
<file name="Essays for 2nd In Class Essays 01.pdf" server="ftp.bizland.com" local="128663458940000000" remote="131345009400000000" Dst="2" />
<file name="Ariston1st In Class Essay.pdf" server="ftp.bizland.com" local="128672534920000000" remote="131345006400000000" Dst="2" />
<file name="Reference Citations in Text.pdf" server="ftp.bizland.com" local="128678604260000000" remote="131345010600000000" Dst="2" />
<file name="3rd in class essay08-09.pdf" server="ftp.bizland.com" local="128686510640000000" remote="131345005800000000" Dst="2" />
<file name="Memorizing Amendments.ppt" server="ftp.bizland.com" local="128487717300000000" remote="131345010600000000" Dst="2" />
<file name="constitution powerpoint AP gov.ppt" server="ftp.bizland.com" local="128498527860000000" remote="131345009400000000" Dst="2" />
<file name="October Sky sample video essay.doc" server="ftp.bizland.com" local="129023892000000000" remote="131345010600000000" Dst="2" />
<file name="reading list for history.doc" server="ftp.bizland.com" local="128511135820000000" remote="131345010600000000" Dst="2" />
<file name="dbq.pdf" server="ftp.bizland.com" local="128824599600000000" remote="131345009400000000" Dst="2" />
<file name="1st DBQ AP USmeredith.pdf" server="ftp.bizland.com" local="128824599280000000" remote="131345005800000000" Dst="2" />
<file name="AP Practice Exam Questions.pdf" server="ftp.bizland.com" local="128824598960000000" remote="131345006400000000" Dst="2" />
<file name="The_First_Gulf_War_and_its_Aftermath2.ppt" server="ftp.bizland.com" local="128849652160000000" remote="131345012400000000" Dst="2" />
<file name="Immigration in the United States of America.pdf" server="ftp.bizland.com" local="128859349500000000" remote="131345010000000000" Dst="2" />
<file name="art 1600-1850.pdf" server="ftp.bizland.com" local="128859348500000000" remote="131345007000000000" Dst="2" />
<file name="P0LPARTIES 1.pdf" server="ftp.bizland.com" local="128859350440000000" remote="131345010600000000" Dst="2" />
<file name="P0LPARTIES 3.pdf" server="ftp.bizland.com" local="128859351380000000" remote="131345010600000000" Dst="2" />
<file name="POLITICAL SCANDALS.pdf" server="ftp.bizland.com" local="128859347640000000" remote="131345010600000000" Dst="2" />
<file name="Extra Study on Unions-1.pdf" server="ftp.bizland.com" local="128860002200000000" remote="131345010000000000" Dst="2" />
<file name="PPC#2.pdf" server="ftp.bizland.com" local="128860004160000000" remote="131345010600000000" Dst="2" />
<file name="women in history1900+.pdf" server="ftp.bizland.com" local="128859997800000000" remote="131345012400000000" Dst="2" />
<file name="women in history.pdf" server="ftp.bizland.com" local="128859352840000000" remote="131345012400000000" Dst="2" />
<file name="Art & Architecture.ppt" server="ftp.bizland.com" local="128859345480000000" remote="131345007000000000" Dst="2" />
<file name="Track01.cda" server="ftp.bizland.com" local="124333956020000000" remote="131345012400000000" Dst="2" />
<file name="ap amhistsyllabus09-10.pdf" server="ftp.bizland.com" local="128873818100000000" remote="131345006400000000" Dst="2" />
<file name="COMPUTER RULES09-10a.pdf" server="ftp.bizland.com" local="128872239500000000" remote="131345009400000000" Dst="2" />
<file name="taylors excellent in class essay 1 09.pdf" server="ftp.bizland.com" local="129024269340000000" remote="131345012400000000" Dst="2" />
<file name="AP American History Syllabusap07.pdf" server="ftp.bizland.com" local="128523975600000000" remote="131345006400000000" Dst="2" />
<file name="Seventeen Years S. Singer.wmv" server="ftp.bizland.com" local="128548318560000000" remote="131345011200000000" Dst="2" />
<file name="Flags of Our Fathersvideo essay 2.doc" server="ftp.bizland.com" local="128532725720000000" remote="131345010000000000" Dst="2" />
<file name="federalistessay.doc" server="ftp.bizland.com" local="128460426240000000" remote="131345010000000000" Dst="2" />
<file name="Evolution of Transportation and Roadways.pptx" server="ftp.bizland.com" local="128563285260000000" remote="131345010000000000" Dst="2" />
<file name="Essay Questions for AP American History.docx" server="ftp.bizland.com" local="128645796320000000" remote="131345009400000000" Dst="2" />
<file name="Essay Questions for AP American History.pdf" server="ftp.bizland.com" local="128645796660000000" remote="131345009400000000" Dst="2" />
<file name="AP American History Syllabusap audit changes08-09.pdf" server="ftp.bizland.com" local="128634707320000000" remote="131345006400000000" Dst="2" />
<file name="Essays for 2nd In Class Essays 08.docx" server="ftp.bizland.com" local="128663293300000000" remote="131345009400000000" Dst="2" />
<file name="Seventeen years Sarah Singer.ppt" server="ftp.bizland.com" local="128866946680000000" remote="131345012400000000" Dst="2" />
<file name="Track02.mp3" server="ftp.bizland.com" local="128841892740000000" remote="131345012400000000" Dst="2" />
<file name="Movie List09-10.pdf" server="ftp.bizland.com" local="128868670640000000" remote="131345010600000000" Dst="2" />
<file name="COMPUTER RULES09-10.pdf" server="ftp.bizland.com" local="128872239220000000" remote="131345009400000000" Dst="2" />
<file name="HONORSAMERICAN HISTORY SYLLABUS09-10AA.pdf" server="ftp.bizland.com" local="128945769160000000" remote="131345010000000000" Dst="2" />
<file name="4th in class essay 09-10.pdf" server="ftp.bizland.com" local="129025149780000000" remote="131345005800000000" Dst="2" />
<file name="SPRING SEMESTER CALENDAR AP 2010A.pdf" server="ftp.bizland.com" local="129089082520000000" remote="131345012400000000" Dst="2" />
<file name="Seventeen years Sarah Singerchange times.pptx" server="ftp.bizland.com" local="129297202800000000" remote="131345012400000000" Dst="2" />
<file name="Seventeen years Sarah Singerchange times.ppt" server="ftp.bizland.com" local="129297202800000000" remote="131345012400000000" Dst="2" />
<file name="ap syllabus 2010-11.pdf" server="ftp.bizland.com" local="129255079320000000" remote="131345006400000000" Dst="2" />
<file name="RAPinstructions.doc" server="ftp.bizland.com" local="129095072600000000" remote="131345010600000000" Dst="2" />
<file name="GROUP GRADING RUBICfor RAP1.pdf" server="ftp.bizland.com" local="129113377580000000" remote="131345010000000000" Dst="2" />
<file name="GRADING EVALUATION RUBRIC FOR RAP.pdf" server="ftp.bizland.com" local="129113378120000000" remote="131345010000000000" Dst="2" />
<file name="sample rap assignment 1789-1815 (2).pdf" server="ftp.bizland.com" local="129119191960000000" remote="131345010600000000" Dst="2" />
<file name="Brooke Theme Paper number 2.wmv" server="ftp.bizland.com" local="129189026380000000" remote="131345109000000000" Dst="2" />
<file name="Essays for 2nd  In Class Essays 10-111.pdf" server="ftp.bizland.com" local="129300648520000000" remote="131345009400000000" Dst="2" />
<file name="3rd in class essay questions 10-11.pdf" server="E:/WEBSITE (new)/" local="129324812200000000" remote="129324812200000000" Dst="-1" />
<file name="3rd in class essay questions 10-11.pdf" server="ftp.bizland.com" local="129324848200000000" remote="131345005800000000" Dst="2" />
<file name="APameressayNICOLE.pdf" server="ftp.bizland.com" local="129328421580000000" remote="131345006400000000" Dst="2" />
<file name="in class essay 3angela.pdf" server="ftp.bizland.com" local="129346558700000000" remote="131345010000000000" Dst="2" />
<file name="in class essay 3angela.docx" server="ftp.bizland.com" local="129346557600000000" remote="131345010000000000" Dst="2" />
<file name="Essays for 2nd  In Class Essays 10-11.docx" server="ftp.bizland.com" local="129300638140000000" remote="131345009400000000" Dst="2" />
<file name="Essays for 2nd  In Class Essays 10-11.pdf" server="ftp.bizland.com" local="129300643400000000" remote="131345009400000000" Dst="2" />
<file name="example thesis by andrew h.pdf" server="ftp.bizland.com" local="129328426820000000" remote="131345010000000000" Dst="2" />
<file name="14Unit 5 and Unit 6 Vocabulary176-182 and 1-40 ashlee.doc" server="ftp.bizland.com" local="129388779680000000" remote="131345005200000000" Dst="2" />
<file name="Allison Banko-music fixed.wmv" server="ftp.bizland.com" local="129344729940000000" remote="131345006400000000" Dst="2" />
<file name="Combined 5.pdf" server="ftp.bizland.com" local="129388784900000000" remote="131345009400000000" Dst="2" />
<file name="Evolution of Transportation and Roadways.ppt" server="ftp.bizland.com" local="129356806740000000" remote="131345009400000000" Dst="2" />
<file name="Untitled-1.jpg" server="ftp.bizland.com" local="129355999780000000" remote="131345012400000000" Dst="2" />
<file name="Analyzing Sources.pdf" server="ftp.bizland.com" local="129682751640000000" remote="131345006400000000" Dst="2" />
<file name="aice syllabus 11-12 (Autosaved)a.pdf" server="ftp.bizland.com" local="129863228540000000" remote="131345005800000000" Dst="2" />
<file name="Dear AICE American History parent 12-13.pdf" server="ftp.bizland.com" local="129863239900000000" remote="131345009400000000" Dst="2" />
<file name="Source Assignment.pdf" server="ftp.bizland.com" local="130512295380000000" remote="131345012400000000" Dst="2" />
</dwsync>